{
  "orders": [
    {
      "id_order": 1,
      "id_client": "1001",
      "first_name": "ヒガ",
      "last_name": "タロウ",
      "email": "higa1@example.com",
      "tel": "11999991001",
      "date": "12月21日（土）",
      "hour": "11~13時",
      "message": "よろしくお願いします。",
      "cakes": [
        {
          "id_cake": 1,
          "name": "ノエルフレーズ ４号",
          "quantity": 10,
          "price": 3700,
          "image": "../image/ノエルフレーズ.jpg",
          "amount": 1
        }
      ],
      "payment": 1,
      "status": 2
    },
    {
      "id_order": 2,
      "id_client": "1002",
      "first_name": "サトウ",
      "last_name": "ハナコ",
      "email": "sato2@example.com",
      "tel": "11999991002",
      "date": "12月22日（日）",
      "hour": "13~17時",
      "message": "",
      "cakes": [
        {
          "id_cake": 2,
          "name": "ショコラドゥ",
          "quantity": 5,
          "price": 4500,
          "image": "../image/ショコラドゥ.jpg",
          "amount": 2
        }
      ],
      "status": 2
    },
    {
      "id_order": 3,
      "id_client": "1003",
      "first_name": "ヤマダ",
      "last_name": "ケンジ",
      "email": "yamada3@example.com",
      "tel": "11999991003",
      "date": "12月23日（月）",
      "hour": "17~19時",
      "message": "メッセージプレートは「ありがとう」で。",
      "cakes": [
        {
          "id_cake": 3,
          "name": "モンブラン",
          "quantity": 7,
          "price": 4000,
          "image": "../image/モンブラン.jpg",
          "amount": 1
        },
        {
          "id_cake": 1,
          "name": "ノエルフレーズ ４号",
          "quantity": 10,
          "price": 3700,
          "image": "../image/ノエルフレーズ.jpg",
          "amount": 1
        }
      ],
      "payment": 2
    },
    {
      "id_order": 4,
      "id_client": "1004",
      "first_name": "イシカワ",
      "last_name": "ミサコ",
      "email": "ishikawa4@example.com",
      "tel": "11999991004",
      "date": "12月24日（火）",
      "hour": "13~17時",
      "message": "",
      "cakes": [
        {
          "id_cake": 4,
          "name": "レアチーズケーキ",
          "quantity": 8,
          "price": 3800,
          "image": "../image/レアチーズケーキ.jpg",
          "amount": 3
        }
      ],
      "payment": 2
    },
    {
      "id_order": 5,
      "id_client": "1005",
      "first_name": "コバヤシ",
      "last_name": "ユウタ",
      "email": "kobayashi5@example.com",
      "tel": "11999991005",
      "date": "12月25日（水）",
      "hour": "11~13時",
      "message": "クリスマスプレゼントをお願いします。",
      "cakes": [
        {
          "id_cake": 2,
          "name": "ショコラドゥ",
          "quantity": 5,
          "price": 4500,
          "image": "../image/ショコラドゥ.jpg",
          "amount": 1
        },
        {
          "id_cake": 5,
          "name": "抹茶ケーキ",
          "quantity": 6,
          "price": 4200,
          "image": "../image/抹茶ケーキ.jpg",
          "amount": 2
        }
      ]
    },
    {
      "id_order": 6,
      "id_client": "1006",
      "first_name": "タナカ",
      "last_name": "マリ",
      "email": "tanaka6@example.com",
      "tel": "11999991006",
      "date": "12月21日（土）",
      "hour": "17~19時",
      "message": "",
      "cakes": [
        {
          "id_cake": 3,
          "name": "モンブラン",
          "quantity": 7,
          "price": 4000,
          "image": "../image/モンブラン.jpg",
          "amount": 1
        }
      ]
    },
    {
      "id_order": 7,
      "id_client": "1007",
      "first_name": "スズキ",
      "last_name": "ケイコ",
      "email": "suzuki7@example.com",
      "tel": "11999991007",
      "date": "12月22日（日）",
      "hour": "13~17時",
      "message": "よろしくお願いします！",
      "cakes": [
        {
          "id_cake": 1,
          "name": "ノエルフレーズ ４号",
          "quantity": 10,
          "price": 3700,
          "image": "../image/ノエルフレーズ.jpg",
          "amount": 2
        }
      ]
    },
    {
      "id_order": 8,
      "id_client": "1008",
      "first_name": "フジモト",
      "last_name": "ショウタ",
      "email": "fujimoto8@example.com",
      "tel": "11999991008",
      "date": "12月23日（月）",
      "hour": "11~13時",
      "message": "",
      "cakes": [
        {
          "id_cake": 4,
          "name": "レアチーズケーキ",
          "quantity": 8,
          "price": 3800,
          "image": "../image/レアチーズケーキ.jpg",
          "amount": 1
        }
      ]
    },
    {
      "id_order": 9,
      "id_client": "1009",
      "first_name": "マツモト",
      "last_name": "リカ",
      "email": "matsumoto9@example.com",
      "tel": "11999991009",
      "date": "12月24日（火）",
      "hour": "13~17時",
      "message": "急ぎです。",
      "cakes": [
        {
          "id_cake": 5,
          "name": "抹茶ケーキ",
          "quantity": 6,
          "price": 4200,
          "image": "../image/抹茶ケーキ.jpg",
          "amount": 3
        }
      ]
    },
    {
      "id_order": 10,
      "id_client": "1010",
      "first_name": "カワムラ",
      "last_name": "ユウジ",
      "email": "kawamura10@example.com",
      "tel": "11999991010",
      "date": "12月25日（水）",
      "hour": "17~19時",
      "message": "",
      "cakes": [
        {
          "id_cake": 2,
          "name": "ショコラドゥ",
          "quantity": 5,
          "price": 4500,
          "image": "../image/ショコラドゥ.jpg",
          "amount": 1
        }
      ]
    },
    {
      "id_order": 11,
      "id_client": "1011",
      "first_name": "ヤマモト",
      "last_name": "サクラ",
      "email": "yamamoto11@example.com",
      "tel": "11999991011",
      "date": "12月21日（土）",
      "hour": "11~13時",
      "message": "ありがとうございます。",
      "cakes": [
        {
          "id_cake": 1,
          "name": "ノエルフレーズ ４号",
          "quantity": 10,
          "price": 3700,
          "image": "../image/ノエルフレーズ.jpg",
          "amount": 1
        },
        {
          "id_cake": 5,
          "name": "抹茶ケーキ",
          "quantity": 6,
          "price": 4200,
          "image": "../image/抹茶ケーキ.jpg",
          "amount": 2
        }
      ]
    },
    {
      "id_order": 12,
      "id_client": "1012",
      "first_name": "タカハシ",
      "last_name": "マコト",
      "email": "takahashi12@example.com",
      "tel": "11999991012",
      "date": "12月22日（日）",
      "hour": "13~17時",
      "message": "",
      "cakes": [
        {
          "id_cake": 3,
          "name": "モンブラン",
          "quantity": 7,
          "price": 4000,
          "image": "../image/モンブラン.jpg",
          "amount": 3
        }
      ]
    },
    {
      "id_order": 13,
      "id_client": "1013",
      "first_name": "コンドウ",
      "last_name": "エリ",
      "email": "kondo13@example.com",
      "tel": "11999991013",
      "date": "12月23日（月）",
      "hour": "17~19時",
      "message": "初めての注文です。",
      "cakes": [
        {
          "id_cake": 4,
          "name": "レアチーズケーキ",
          "quantity": 8,
          "price": 3800,
          "image": "../image/レアチーズケーキ.jpg",
          "amount": 2
        }
      ]
    },
    {
      "id_order": 14,
      "id_client": "1014",
      "first_name": "ヤマグチ",
      "last_name": "ケイ",
      "email": "yamaguchi14@example.com",
      "tel": "11999991014",
      "date": "12月24日（火）",
      "hour": "13~17時",
      "message": "",
      "cakes": [
        {
          "id_cake": 5,
          "name": "抹茶ケーキ",
          "quantity": 6,
          "price": 4200,
          "image": "../image/抹茶ケーキ.jpg",
          "amount": 1
        },
        {
          "id_cake": 2,
          "name": "ショコラドゥ",
          "quantity": 5,
          "price": 4500,
          "image": "../image/ショコラドゥ.jpg",
          "amount": 1
        }
      ]
    },
    {
      "id_order": 15,
      "id_client": "1015",
      "first_name": "ナカムラ",
      "last_name": "アキラ",
      "email": "nakamura15@example.com",
      "tel": "11999991015",
      "date": "12月25日（水）",
      "hour": "11~13時",
      "message": "よろしくお願いします。",
      "cakes": [
        {
          "id_cake": 1,
          "name": "ノエルフレーズ ４号",
          "quantity": 10,
          "price": 3700,
          "image": "../image/ノエルフレーズ.jpg",
          "amount": 3
        }
      ]
    },
    {
      "id_order": 16,
      "id_client": "1016",
      "first_name": "ハセガワ",
      "last_name": "ミツル",
      "email": "hasegawa16@example.com",
      "tel": "11999991016",
      "date": "12月21日（土）",
      "hour": "17~19時",
      "message": "",
      "cakes": [
        {
          "id_cake": 3,
          "name": "モンブラン",
          "quantity": 7,
          "price": 4000,
          "image": "../image/モンブラン.jpg",
          "amount": 2
        }
      ]
    },
    {
      "id_order": 17,
      "id_client": "1017",
      "first_name": "カトウ",
      "last_name": "マユミ",
      "email": "kato17@example.com",
      "tel": "11999991017",
      "date": "12月22日（日）",
      "hour": "13~17時",
      "message": "ありがとうございます。",
      "cakes": [
        {
          "id_cake": 4,
          "name": "レアチーズケーキ",
          "quantity": 8,
          "price": 3800,
          "image": "../image/レアチーズケーキ.jpg",
          "amount": 1
        }
      ]
    },
    {
      "id_order": 18,
      "id_client": "1018",
      "first_name": "マツイ",
      "last_name": "アヤ",
      "email": "matsui18@example.com",
      "tel": "11999991018",
      "date": "12月23日（月）",
      "hour": "11~13時",
      "message": "",
      "cakes": [
        {
          "id_cake": 2,
          "name": "ショコラドゥ",
          "quantity": 5,
          "price": 4500,
          "image": "../image/ショコラドゥ.jpg",
          "amount": 2
        }
      ],
      "payment": 2
    },
    {
      "id_order": 19,
      "id_client": "1019",
      "first_name": "ナカジマ",
      "last_name": "ユウコ",
      "email": "nakajima19@example.com",
      "tel": "11999991019",
      "date": "12月24日（火）",
      "hour": "13~17時",
      "message": "急ぎでお願いします。",
      "cakes": [
        {
          "id_cake": 5,
          "name": "抹茶ケーキ",
          "quantity": 6,
          "price": 4200,
          "image": "../image/抹茶ケーキ.jpg",
          "amount": 1
        }
      ]
    },
    {
      "id_client": "4234",
      "first_name": "testeqr",
      "last_name": "testeqr",
      "email": "a@a.com",
      "tel": "24234234",
      "date": "12月21日（土）",
      "hour": "11~13時",
      "message": "teste qr code",
      "cakes": [
        {
          "id_cake": 9,
          "name": "⑤ ノエルレア　１６cm x １１cm ￥４,６００",
          "quantity": 5,
          "price": 4600,
          "image": "../image/ノエルレア.jpg",
          "amount": 1
        },
        {
          "id_cake": 9,
          "name": "⑤ ノエルレア　１６cm x １１cm ￥４,６００",
          "quantity": 5,
          "price": 4600,
          "image": "../image/ノエルレア.jpg",
          "amount": 1
        },
        {
          "id_cake": 9,
          "name": "⑤ ノエルレア　１６cm x １１cm ￥４,６００",
          "quantity": 5,
          "price": 4600,
          "image": "../image/ノエルレア.jpg",
          "amount": 3
        }
      ],
      "id_order": 20
    },
    {
      "id_client": "5476",
      "first_name": "teste",
      "last_name": "teste",
      "email": "A@a.com",
      "tel": "2564365476",
      "date": "12月21日（土）",
      "hour": "11~13時",
      "message": "rfjytf",
      "cakes": [
        {
          "id_cake": 5,
          "name": "② ノエルショコラ ５号 ￥４,８００",
          "quantity": 5,
          "price": 4800,
          "image": "../image/ノエルショコラ.jpg",
          "amount": 1
        },
        {
          "id_cake": 9,
          "name": "⑤ ノエルレア　１６cm x １１cm ￥４,６００",
          "quantity": 5,
          "price": 4600,
          "image": "../image/ノエルレア.jpg",
          "amount": 1
        }
      ],
      "id_order": 21
    },
    {
      "id_client": "3534",
      "first_name": "sdf",
      "last_name": "sdf",
      "email": "shimitsutanaka@gmail.com",
      "tel": "445343453534",
      "date": "12月21日（土）",
      "hour": "13~17時",
      "message": "ertyertyertyertyerty",
      "cakes": [
        {
          "id_cake": 9,
          "name": "⑤ ノエルレア　１６cm x １１cm ￥４,６００",
          "quantity": 5,
          "price": 4600,
          "image": "../image/ノエルレア.jpg",
          "amount": 1
        },
        {
          "id_cake": 2,
          "name": "① ノエルフレーズ ５号 ￥４,６００",
          "quantity": 8,
          "price": 4600,
          "image": "../image/ノエルフレーズ.jpg",
          "amount": 1
        }
      ],
      "id_order": 22
    },
    {
      "id_client": "2222",
      "first_name": "asas",
      "last_name": "asas",
      "email": "shimitsutanaka@gmail.com",
      "tel": "232222",
      "date": "12月21日（土）",
      "hour": "11~13時",
      "message": "wqeqweqwe",
      "cakes": [
        {
          "id_cake": 2,
          "name": "① ノエルフレーズ ５号 ￥４,６００",
          "quantity": 8,
          "price": 4600,
          "image": "../image/ノエルフレーズ.jpg",
          "amount": 1
        },
        {
          "id_cake": 8,
          "name": "④ フェデルタ　５号　￥５,６００（完売）",
          "quantity": 5,
          "price": 5600,
          "image": "../image/フェデルタ.jpg",
          "amount": 2
        },
        {
          "id_cake": 11,
          "name": "⑦ クリスマスロール　１７cm ￥３,２００",
          "quantity": 5,
          "price": 3200,
          "image": "../image/クリスマスロール.jpg",
          "amount": 1
        },
        {
          "id_cake": 5,
          "name": "② ノエルショコラ ５号 ￥４,８００",
          "quantity": 5,
          "price": 4800,
          "image": "../image/ノエルショコラ.jpg",
          "amount": 1
        }
      ],
      "id_order": 23
    },
    {
      "id_client": "2222",
      "first_name": "asas",
      "last_name": "asas",
      "email": "shimitsutanaka@gmail.com",
      "tel": "232222",
      "date": "12月21日（土）",
      "hour": "11~13時",
      "message": "wqeqweqwe",
      "cakes": [
        {
          "id_cake": 2,
          "name": "① ノエルフレーズ ５号 ￥４,６００",
          "quantity": 8,
          "price": 4600,
          "image": "../image/ノエルフレーズ.jpg",
          "amount": 1
        },
        {
          "id_cake": 8,
          "name": "④ フェデルタ　５号　￥５,６００（完売）",
          "quantity": 5,
          "price": 5600,
          "image": "../image/フェデルタ.jpg",
          "amount": 2
        },
        {
          "id_cake": 11,
          "name": "⑦ クリスマスロール　１７cm ￥３,２００",
          "quantity": 5,
          "price": 3200,
          "image": "../image/クリスマスロール.jpg",
          "amount": 1
        },
        {
          "id_cake": 5,
          "name": "② ノエルショコラ ５号 ￥４,８００",
          "quantity": 5,
          "price": 4800,
          "image": "../image/ノエルショコラ.jpg",
          "amount": 1
        }
      ],
      "id_order": 24
    },
    {
      "id_client": "4234",
      "first_name": "testesss",
      "last_name": "testsss",
      "email": "shimitsutanaka@gmail.com",
      "tel": "234234234",
      "date": "12月21日（土）",
      "hour": "11~13時",
      "message": "wqeweqeqwe",
      "cakes": [
        {
          "id_cake": 9,
          "name": "⑤ ノエルレア　１６cm x １１cm ￥４,６００",
          "quantity": 5,
          "price": 4600,
          "image": "../image/ノエルレア.jpg",
          "amount": 1
        }
      ],
      "id_order": 25,
      "status": "pendente",
      "payment": "pendente"
    }
  ]
}